mcs/drivers/core/__init__.py
mcs/drivers/core/mcs_base_orchestrator.py
mcs/drivers/core/mcs_driver_interface.py
mcs/drivers/core/mcs_tool_driver_interface.py
mcs_drivers_core-0.2.dist-info/METADATA
mcs_drivers_core-0.2.dist-info/WHEEL
mcs_drivers_core-0.2.dist-info/top_level.txt
mcs_drivers_core-0.2.dist-info/RECORD
