Metadata-Version: 2.4
Name: mcs-drivers-core
Version: 0.2
Summary: Core driver contract for the Model Context Standard.
Author-email: Danny Gerst <danny@dannygerst.de>
License-Expression: Apache-2.0
Project-URL: Homepage, https://www.modelcontextstandard.io
Project-URL: Source, https://github.com/modelcontextstandard/python-sdk
Keywords: mcs,modelcontextstandard,mcs-driver,mcs-drivers,mcs-tools,mcs-orchestrator,python-sdk,python,function-calling,llms,integration,driver
Requires-Python: >=3.9
